pycdo/__about__.py
pycdo/__init__.py
pycdo/cdo_cache.py
pycdo/cdo_operation.py
pycdo/cdo_operator.py
pycdo/cdo_options.py
pycdo/debug.py
pycdo/ephemeral_file.py
pycdo/example_data.py
pycdo/data/geopotential.nc
pycdo-0.2.1.dist-info/METADATA
pycdo-0.2.1.dist-info/WHEEL
pycdo-0.2.1.dist-info/licenses/LICENSE
pycdo-0.2.1.dist-info/RECORD
