Metadata-Version: 2.4
Name: pycdo
Version: 0.2.1
Summary: Python wrapper of the Climate Data Operators
Project-URL: Homepage, https://github.com/eliocamp/pycdo
Project-URL: Source Code, https://github.com/eliocamp/pycdo
Project-URL: Bug Tracker, https://github.com/eliocamp/pycdo/issues
Project-URL: Documentation, https://github.com/eliocamp/pycdo/blob/main/README.md
Project-URL: Download, https://pypi.org/project/pycdo/#files
Author-email: Elio Campitelli <eliocampitelli@gmail.com>
License-Expression: MIT
License-File: LICENSE
Classifier: Development Status :: 2 - Pre-Alpha
Classifier: Intended Audience :: Science/Research
Classifier: License :: OSI Approved :: MIT License
Classifier: Operating System :: OS Independent
Classifier: Programming Language :: Python :: 3 :: Only
Requires-Python: >=3.10
Provides-Extra: build
Requires-Dist: pip-audit; extra == 'build'
Requires-Dist: twine; extra == 'build'
Provides-Extra: dev
Requires-Dist: hatch; extra == 'dev'
Requires-Dist: pre-commit; extra == 'dev'
Provides-Extra: docs
Requires-Dist: myst-parser>=4.0; extra == 'docs'
Requires-Dist: pydata-sphinx-theme~=0.16; extra == 'docs'
Requires-Dist: sphinx-autoapi>=3.6.0; extra == 'docs'
Requires-Dist: sphinx-autobuild>=2024.10.3; extra == 'docs'
Requires-Dist: sphinx-copybutton>=0.5.2; extra == 'docs'
Requires-Dist: sphinx-design>=0.6.1; extra == 'docs'
Requires-Dist: sphinx~=8.0; extra == 'docs'
Provides-Extra: tests
Requires-Dist: pytest; extra == 'tests'
Requires-Dist: pytest-cov; extra == 'tests'
Requires-Dist: pytest-raises; extra == 'tests'
Requires-Dist: pytest-randomly; extra == 'tests'
Requires-Dist: pytest-xdist; extra == 'tests'
